{
  "DB_LevelCheckChild1Data" : {
    "_id" : "wm-DB_LevelCheckChild1Data-wm.LiveVariable-1539337510016",
    "name" : "DB_LevelCheckChild1Data",
    "owner" : "Page",
    "category" : "wm.LiveVariable",
    "dataBinding" : [ ],
    "operation" : "read",
    "dataSet" : [ ],
    "type" : "Child1",
    "isList" : true,
    "saveInPhonegap" : false,
    "maxResults" : 20,
    "designMaxResults" : 10,
    "inFlightBehavior" : "executeLast",
    "startUpdate" : true,
    "autoUpdate" : true,
    "transformationRequired" : false,
    "liveSource" : "DB_LevelCheck",
    "ignoreCase" : true,
    "matchMode" : "startignorecase",
    "orderBy" : "childId1 asc",
    "propertiesMap" : {
      "columns" : [ {
        "fieldName" : "parent1",
        "type" : "integer",
        "fullyQualifiedType" : "integer",
        "columnName" : "CHILD_ID1",
        "isPrimaryKey" : true,
        "notNull" : true,
        "length" : 0,
        "precision" : 10,
        "generator" : "assigned",
        "isRelated" : true,
        "relatedTableName" : "PARENT1",
        "relatedEntityName" : "Parent1",
        "relatedColumnName" : "childId1",
        "relatedFieldName" : "parent1.parentId",
        "isList" : false,
        "targetTable" : "PARENT1",
        "scale" : 0,
        "columns" : [ {
          "fieldName" : "parentId",
          "type" : "integer",
          "fullyQualifiedType" : "integer",
          "columnName" : "PARENT_ID",
          "isPrimaryKey" : true,
          "notNull" : true,
          "length" : 0,
          "precision" : 10,
          "generator" : "assigned",
          "isRelated" : false,
          "scale" : 0
        }, {
          "fieldName" : "parentCol1",
          "type" : "string",
          "fullyQualifiedType" : "string",
          "columnName" : "PARENT_COL1",
          "isPrimaryKey" : false,
          "notNull" : false,
          "length" : 255,
          "precision" : 0,
          "generator" : "assigned",
          "isRelated" : false,
          "scale" : 0
        }, {
          "fieldName" : "parentCol2",
          "type" : "string",
          "fullyQualifiedType" : "string",
          "columnName" : "PARENT_COL2",
          "isPrimaryKey" : false,
          "notNull" : false,
          "length" : 255,
          "precision" : 0,
          "generator" : "assigned",
          "isRelated" : false,
          "scale" : 0
        }, {
          "fieldName" : "parentCol3",
          "type" : "string",
          "fullyQualifiedType" : "string",
          "columnName" : "PARENT_COL3",
          "isPrimaryKey" : false,
          "notNull" : false,
          "length" : 255,
          "precision" : 0,
          "generator" : "assigned",
          "isRelated" : false,
          "scale" : 0
        } ]
      }, {
        "fieldName" : "childCol1",
        "type" : "string",
        "fullyQualifiedType" : "string",
        "columnName" : "CHILD_COL1",
        "isPrimaryKey" : false,
        "notNull" : false,
        "length" : 255,
        "precision" : 0,
        "generator" : "assigned",
        "isRelated" : false,
        "scale" : 0
      }, {
        "fieldName" : "childCol2",
        "type" : "string",
        "fullyQualifiedType" : "string",
        "columnName" : "CHILD_COL2",
        "isPrimaryKey" : false,
        "notNull" : false,
        "length" : 255,
        "precision" : 0,
        "generator" : "assigned",
        "isRelated" : false,
        "scale" : 0
      }, {
        "fieldName" : "childCol3",
        "type" : "string",
        "fullyQualifiedType" : "string",
        "columnName" : "CHILD_COL3",
        "isPrimaryKey" : false,
        "notNull" : false,
        "length" : 255,
        "precision" : 0,
        "generator" : "assigned",
        "isRelated" : false,
        "scale" : 0
      } ],
      "entityName" : "Child1",
      "fullyQualifiedName" : "com.auto_mcderpvqcs.db_levelcheck.Child1",
      "tableType" : "TABLE",
      "primaryFields" : [ "childId1" ]
    },
    "isDefault" : true,
    "bindCount" : 1,
    "tableName" : "CHILD1",
    "tableType" : "TABLE",
    "properties" : [ "parent1" ],
    "relatedTables" : [ {
      "columnName" : "parent1",
      "relationName" : "parent1",
      "type" : "Parent1",
      "watchOn" : "DB_LevelCheckParent1Data",
      "package" : "com.auto_mcderpvqcs.db_levelcheck.Child1"
    } ],
    "filterExpressions" : { },
    "package" : "com.auto_mcderpvqcs.db_levelcheck.Child1"
  },
  "DB_LevelCheckParent1Data" : {
    "_id" : "wm-DB_LevelCheckParent1Data-wm.LiveVariable-1539339177012",
    "name" : "DB_LevelCheckParent1Data",
    "owner" : "Page",
    "category" : "wm.LiveVariable",
    "dataBinding" : [ ],
    "operation" : "read",
    "dataSet" : [ ],
    "type" : "Parent1",
    "isList" : true,
    "saveInPhonegap" : false,
    "maxResults" : 20,
    "designMaxResults" : 10,
    "inFlightBehavior" : "executeLast",
    "startUpdate" : true,
    "autoUpdate" : true,
    "transformationRequired" : false,
    "liveSource" : "DB_LevelCheck",
    "ignoreCase" : true,
    "matchMode" : "startignorecase",
    "orderBy" : "parentId asc",
    "propertiesMap" : {
      "columns" : [ {
        "fieldName" : "parentId",
        "type" : "integer",
        "fullyQualifiedType" : "integer",
        "columnName" : "PARENT_ID",
        "isPrimaryKey" : true,
        "notNull" : true,
        "length" : 0,
        "precision" : 10,
        "generator" : "assigned",
        "isRelated" : false,
        "scale" : 0
      }, {
        "fieldName" : "parentCol1",
        "type" : "string",
        "fullyQualifiedType" : "string",
        "columnName" : "PARENT_COL1",
        "isPrimaryKey" : false,
        "notNull" : false,
        "length" : 255,
        "precision" : 0,
        "generator" : "assigned",
        "isRelated" : false,
        "scale" : 0
      }, {
        "fieldName" : "parentCol2",
        "type" : "string",
        "fullyQualifiedType" : "string",
        "columnName" : "PARENT_COL2",
        "isPrimaryKey" : false,
        "notNull" : false,
        "length" : 255,
        "precision" : 0,
        "generator" : "assigned",
        "isRelated" : false,
        "scale" : 0
      }, {
        "fieldName" : "parentCol3",
        "type" : "string",
        "fullyQualifiedType" : "string",
        "columnName" : "PARENT_COL3",
        "isPrimaryKey" : false,
        "notNull" : false,
        "length" : 255,
        "precision" : 0,
        "generator" : "assigned",
        "isRelated" : false,
        "scale" : 0
      } ],
      "entityName" : "Parent1",
      "fullyQualifiedName" : "com.auto_mcderpvqcs.db_levelcheck.Parent1",
      "tableType" : "TABLE",
      "primaryFields" : [ "parentId" ]
    },
    "isDefault" : true,
    "bindCount" : 1,
    "tableName" : "PARENT1",
    "tableType" : "TABLE",
    "properties" : [ ],
    "relatedTables" : [ ],
    "filterExpressions" : { },
    "package" : "com.auto_mcderpvqcs.db_levelcheck.Parent1"
  },
  "MyJavaServiceSampleJavaOperation" : {
    "_id" : "wm-MyJavaServiceSampleJavaOperation-wm.ServiceVariable-1539336854795",
    "name" : "MyJavaServiceSampleJavaOperation",
    "owner" : "Page",
    "category" : "wm.ServiceVariable",
    "dataBinding" : [ ],
    "type" : "string",
    "service" : "MyJavaService",
    "operation" : "sampleJavaOperation",
    "operationId" : "MyJavaController_sampleJavaOperation",
    "operationType" : "get",
    "serviceType" : "JavaService",
    "dataSet" : [ ],
    "isList" : false,
    "maxResults" : 20,
    "startUpdate" : true,
    "autoUpdate" : true,
    "inFlightBehavior" : "executeLast",
    "transformationRequired" : false,
    "saveInPhonegap" : false,
    "isDefault" : true,
    "controller" : "MyJava"
  }
}